htc_tree/__init__.py
htc_tree/node.py
htc_tree/stock_model_wrappers.py
htc_tree-0.0.6.dist-info/LICENSE
htc_tree-0.0.6.dist-info/METADATA
htc_tree-0.0.6.dist-info/WHEEL
htc_tree-0.0.6.dist-info/top_level.txt
htc_tree-0.0.6.dist-info/RECORD
